mtllm/__init__.py
mtllm-0.4.1.dist-info/METADATA
mtllm-0.4.1.dist-info/WHEEL
mtllm-0.4.1.dist-info/RECORD
